{
  "quiz_id": "course_ea7f494d",
  "answers": {
    "course_ea7f494d_q1": "B",
    "course_ea7f494d_q2": "C",
    "course_ea7f494d_q3": "C",
    "course_ea7f494d_q4": "C",
    "course_ea7f494d_q5": "C",
    "course_ea7f494d_q6": "B",
    "course_ea7f494d_q7": "B",
    "course_ea7f494d_q8": "C",
    "course_ea7f494d_q9": "C",
    "course_ea7f494d_q10": "B",
    "course_ea7f494d_q11": "C",
    "course_ea7f494d_q12": "B",
    "course_ea7f494d_q13": "B",
    "course_ea7f494d_q14": "B",
    "course_ea7f494d_q15": "C",
    "course_ea7f494d_q16": "A",
    "course_ea7f494d_q17": "C",
    "course_ea7f494d_q18": "D",
    "course_ea7f494d_q19": "B",
    "course_ea7f494d_q20": "B",
    "course_ea7f494d_q21": "B",
    "course_ea7f494d_q22": "B",
    "course_ea7f494d_q23": "B",
    "course_ea7f494d_q24": "C",
    "course_ea7f494d_q25": "B",
    "course_ea7f494d_q26": "C",
    "course_ea7f494d_q27": "B",
    "course_ea7f494d_q28": "C",
    "course_ea7f494d_q29": "D",
    "course_ea7f494d_q30": "B",
    "course_ea7f494d_q31": "C",
    "course_ea7f494d_q32": "C",
    "course_ea7f494d_q33": "B",
    "course_ea7f494d_q34": "B",
    "course_ea7f494d_q35": "C",
    "course_ea7f494d_q36": "B",
    "course_ea7f494d_q37": "B",
    "course_ea7f494d_q38": "C",
    "course_ea7f494d_q39": "B",
    "course_ea7f494d_q40": "B"
  },
  "quiz": {
    "title": "Final Course Quiz: Comprehensive Study of Nutrition and Changes in Matter",
    "total_questions": 40,
    "quiz_type": "course",
    "created_at": "2025-09-19T08:58:58.212445"
  }
}